glbuild/__init__.py
glbuild/cli/__init__.py
glbuild/cli/main.py
glbuild/constants.py
glbuild/glbuild.py
glbuild/storage/__init__.py
glbuild/storage/abstract_storage.py
glbuild/storage/local_storage.py
glbuild/utils/__init__.py
glbuild/utils/utils.py
glbuild-0.1.27.dist-info/METADATA
glbuild-0.1.27.dist-info/WHEEL
glbuild-0.1.27.dist-info/entry_points.txt
glbuild-0.1.27.dist-info/licenses/LICENSE
glbuild-0.1.27.dist-info/RECORD
