Metadata-Version: 2.4
Name: glbuild
Version: 0.1.27
Summary: A lightweight library and CLI tool for historical GitLab build data and logs collection.
License: MIT
License-File: LICENSE
Author: Henri Aïdasso
Author-email: ahenrij@gmail.com
Requires-Python: >=3.10,<4.0
Classifier: Development Status :: 4 - Beta
Classifier: License :: OSI Approved :: MIT License
Classifier: Programming Language :: Python :: 3
Classifier: Programming Language :: Python :: 3.10
Classifier: Programming Language :: Python :: 3.11
Classifier: Programming Language :: Python :: 3.12
Classifier: Programming Language :: Python :: 3.13
Classifier: Programming Language :: Python :: 3.14
Classifier: Topic :: Database
Classifier: Topic :: Software Development :: Libraries :: Python Modules
Classifier: Topic :: Utilities
Requires-Dist: click (>=8.1.7,<9.0.0)
Requires-Dist: json-repair (>=0.30.0,<0.31.0)
Requires-Dist: pydantic (>=2.7.1,<3.0.0)
Requires-Dist: pydantic-settings (>=2.2.1,<3.0.0)
Requires-Dist: python-gitlab (>=4.5.0,<5.0.0)
Requires-Dist: requests (>=2.31.0,<3.0.0)
Requires-Dist: simplejson (>=3.19.3,<4.0.0)
Requires-Dist: toml (>=0.10.2,<0.11.0)
Requires-Dist: tqdm (>=4.66.4,<5.0.0)
Project-URL: Repository, https://gitlab.com/ets-devops/pipelines/digital-twin/glbuild
